gcpq/__init__.py
gcpq/cfg_service.py
gcpq/config/services.yaml
gcpq/console_utils.py
gcpq/gcp_cli_service.py
gcpq/gcp_sections_service.py
gcpq/main.py
gcp_quick_utils-0.3.1.dist-info/METADATA
gcp_quick_utils-0.3.1.dist-info/WHEEL
gcp_quick_utils-0.3.1.dist-info/entry_points.txt
gcp_quick_utils-0.3.1.dist-info/RECORD
