Metadata-Version: 2.1
Name: gcp-quick-utils
Version: 0.3.1
Summary: Tools to help you navigate through GCP
Home-page: https://github.com/faahren/gcp-quick-utils.git
License: MIT
Author: Guillaume W
Author-email: guillaume.luc.wagner@gmail.com
Requires-Python: >=3.7
Classifier: License :: OSI Approved :: MIT License
Classifier: Programming Language :: Python :: 3
Classifier: Programming Language :: Python :: 3.7
Classifier: Programming Language :: Python :: 3.8
Classifier: Programming Language :: Python :: 3.9
Classifier: Programming Language :: Python :: 3.10
Classifier: Programming Language :: Python :: 3.11
Classifier: Programming Language :: Python :: 3.12
Requires-Dist: click (>=8.1.7,<9.0.0)
Requires-Dist: pyyaml (>=6.0.1,<7.0.0)
